module/__init__.py
module/hi.py
my_module_goto95-1.0.dist-info/METADATA
my_module_goto95-1.0.dist-info/WHEEL
my_module_goto95-1.0.dist-info/top_level.txt
my_module_goto95-1.0.dist-info/RECORD
