Metadata-Version: 2.1
Name: my-module-goto95
Version: 1.0
Summary: UNKNOWN
Author: GoTo95
Author-email: uraprudnikov@yandex.ru
License: UNKNOWN
Platform: UNKNOWN
Requires-Dist: requests
Requires-Dist: numpy
